{"cameraMode":{"drawMode":0,"name":"Shaded","section":"Shading Mode"},"sceneLighting":true,"audioPlay":false,"sceneViewState":{"m_AlwaysRefresh":false,"showFog":true,"showSkybox":true,"showFlares":true,"showImageEffects":true,"showParticleSystems":true,"showVisualEffectGraphs":true,"m_FxEnabled":true},"in2DMode":false,"pivot":{"x":-11.08234977722168,"y":103.1557846069336,"z":23.17995262145996},"rotation":{"x":0.012350977398455143,"y":-0.40361061692237856,"z":0.00544907758012414,"w":0.9148313403129578},"size":9.201336860656739,"orthographic":false}